Metadata-Version: 2.1
Name: IMMP
Version: 0.12.1
Summary: A modular processing platform for instant messages.
Home-page: https://immp.t.allofti.me
Author: Terrance
Author-email: immp@terrance.allofti.me
License: BSD 3-Clause License
Platform: Any
Classifier: Development Status :: 4 - Beta
Classifier: Intended Audience :: Developers
Classifier: Topic :: Communications :: Chat
Classifier: Topic :: Software Development :: Libraries
Requires-Python: >=3.7
License-File: LICENSE.txt
Provides-Extra: console
Requires-Dist: aioconsole (>=0.1.14) ; extra == 'console'
Provides-Extra: db
Requires-Dist: tortoise-orm (>=0.15.0) ; extra == 'db'
Provides-Extra: discord
Requires-Dist: aiohttp (>=3.0.0) ; extra == 'discord'
Requires-Dist: discord.py (>=2.0.0) ; extra == 'discord'
Requires-Dist: emoji (>=1.6.2) ; extra == 'discord'
Provides-Extra: hangouts
Requires-Dist: aiohttp (>=3.0.0) ; extra == 'hangouts'
Requires-Dist: hangups (>=0.4.11) ; extra == 'hangouts'
Provides-Extra: runner
Requires-Dist: anyconfig (>=0.11.1) ; extra == 'runner'
Requires-Dist: ruamel.yaml (>=0.15.75) ; extra == 'runner'
Provides-Extra: slack
Requires-Dist: aiohttp (>=3.0.0) ; extra == 'slack'
Requires-Dist: emoji (>=1.6.2) ; extra == 'slack'
Provides-Extra: sync
Requires-Dist: emoji (>=1.2.1) ; extra == 'sync'
Requires-Dist: jinja2 (>=2.6) ; extra == 'sync'
Provides-Extra: telegram
Requires-Dist: aiohttp (>=3.0.0) ; extra == 'telegram'
Requires-Dist: telethon (>=1.9.0) ; extra == 'telegram'
Provides-Extra: uv
Requires-Dist: uvloop (>=0.12.0) ; extra == 'uv'
Provides-Extra: web
Requires-Dist: aiohttp (>=3.0.0) ; extra == 'web'
Requires-Dist: aiohttp-jinja2 (>=1.0.0) ; extra == 'web'
Provides-Extra: webui
Requires-Dist: docutils (>=0.16) ; extra == 'webui'
